CMakeLists.txt
LICENSE
MANIFEST.in
README.md
setup.py
pybind11/CMakeLists.txt
pybind11/include/pybind11/attr.h
pybind11/include/pybind11/buffer_info.h
pybind11/include/pybind11/cast.h
pybind11/include/pybind11/chrono.h
pybind11/include/pybind11/complex.h
pybind11/include/pybind11/eigen.h
pybind11/include/pybind11/embed.h
pybind11/include/pybind11/eval.h
pybind11/include/pybind11/functional.h
pybind11/include/pybind11/iostream.h
pybind11/include/pybind11/numpy.h
pybind11/include/pybind11/operators.h
pybind11/include/pybind11/options.h
pybind11/include/pybind11/pybind11.h
pybind11/include/pybind11/pytypes.h
pybind11/include/pybind11/stl.h
pybind11/include/pybind11/stl_bind.h
pybind11/include/pybind11/detail/class.h
pybind11/include/pybind11/detail/common.h
pybind11/include/pybind11/detail/descr.h
pybind11/include/pybind11/detail/init.h
pybind11/include/pybind11/detail/internals.h
pybind11/include/pybind11/detail/typeid.h
pybind11/tests/CMakeLists.txt
pybind11/tests/test_cmake_build/CMakeLists.txt
pybind11/tests/test_cmake_build/installed_embed/CMakeLists.txt
pybind11/tests/test_cmake_build/installed_function/CMakeLists.txt
pybind11/tests/test_cmake_build/installed_target/CMakeLists.txt
pybind11/tests/test_cmake_build/subdirectory_embed/CMakeLists.txt
pybind11/tests/test_cmake_build/subdirectory_function/CMakeLists.txt
pybind11/tests/test_cmake_build/subdirectory_target/CMakeLists.txt
pybind11/tests/test_embed/CMakeLists.txt
pybind11/tools/FindCatch.cmake
pybind11/tools/FindEigen3.cmake
pybind11/tools/FindPythonLibsNew.cmake
pybind11/tools/pybind11Tools.cmake
resmcseg/__init__.py
resmcseg.egg-info/PKG-INFO
resmcseg.egg-info/SOURCES.txt
resmcseg.egg-info/dependency_links.txt
resmcseg.egg-info/not-zip-safe
resmcseg.egg-info/top_level.txt
resmcseg/data/zh17.tif
resmcseg/data/zh17_GT.tif
src/bindings.cpp
src/cmetrics.cpp
src/cmetrics.hpp
src/resmcseg.egg-info/PKG-INFO
src/resmcseg.egg-info/SOURCES.txt
src/resmcseg.egg-info/dependency_links.txt
src/resmcseg.egg-info/not-zip-safe
src/resmcseg.egg-info/top_level.txt