Metadata-Version: 2.1
Name: resmcseg
Version: 0.1.2
Summary: Library for Deep Residual Multiscale Segmenter
Home-page: UNKNOWN
Author: Lianfa Li
Author-email: lspatial@gmail.com
License: UNKNOWN
Platform: UNKNOWN
